fritzhome/__init__.py
fritzhome/__main__.py
fritzhome/actor.py
fritzhome/fritz.py
fritzhome-1.0.5.dist-info/DESCRIPTION.rst
fritzhome-1.0.5.dist-info/METADATA
fritzhome-1.0.5.dist-info/RECORD
fritzhome-1.0.5.dist-info/WHEEL
fritzhome-1.0.5.dist-info/entry_points.txt
fritzhome-1.0.5.dist-info/metadata.json
fritzhome-1.0.5.dist-info/top_level.txt
