Metadata-Version: 2.0
Name: fritzhome
Version: 1.0.5
Summary: Query information from your FRITZ!Box (mostly energy)
Home-page: https://github.com/DerMitch/fritzbox-smarthome
Author: Michael Mayr
Author-email: michael@dermitch.de
License: MIT
Keywords: fritzbox smarthome avm energy
Platform: UNKNOWN
Classifier: Development Status :: 4 - Beta
Classifier: License :: OSI Approved :: MIT License
Classifier: Programming Language :: Python :: 2
Classifier: Programming Language :: Python :: 2.7
Classifier: Programming Language :: Python :: 3
Classifier: Programming Language :: Python :: 3.5
Classifier: Programming Language :: Python :: 3.6
Requires-Dist: requests (>=2.12.0)
Requires-Dist: click (>=6.0.0)
